dynamics_utils/__init__.py
dynamics_utils/math.py
dynamics_utils/msm.py
dynamics_utils/nmr.py
dynamics_utils/potential.py
dynamics_utils/file_handling/__init__.py
dynamics_utils/file_handling/load_files.py
dynamics_utils/sampling/__init__.py
dynamics_utils/sampling/sde.py
dynamics_utils/utils/__init__.py
dynamics_utils/utils/decorators.py
dynamics_utils/utils/torch_utils.py
dynamics_utils-0.0.2.dist-info/METADATA
dynamics_utils-0.0.2.dist-info/WHEEL
dynamics_utils-0.0.2.dist-info/top_level.txt
dynamics_utils-0.0.2.dist-info/RECORD
