Metadata-Version: 2.1
Name: dynamics_utils
Version: 0.0.2
Summary: Utils for dealing with dynamic data (MSM, NMR, etc.)
Home-page: https://github.com/chrisdkolloff/dynamics_utils.git
Author: chrisdkolloff
Author-email: chrisdkolloff@gmail.com
Requires-Dist: numpy
Requires-Dist: torch
Requires-Dist: deeptime
Requires-Dist: h5py
